README.md
pyproject.toml
setup.cfg
setup.py
ZSGF/__init__.py
ZSGF.Client.egg-info/PKG-INFO
ZSGF.Client.egg-info/SOURCES.txt
ZSGF.Client.egg-info/dependency_links.txt
ZSGF.Client.egg-info/requires.txt
ZSGF.Client.egg-info/top_level.txt
ZSGF/Client/__init__.py
ZSGF/Client/api_client.py
ZSGF/Client/api_response.py
ZSGF/Client/configuration.py
ZSGF/Client/exceptions.py
ZSGF/Client/py.typed
ZSGF/Client/rest.py
ZSGF/Client/api/__init__.py
ZSGF/Client/api/access_token_api.py
ZSGF/Client/api/alipay_api.py
ZSGF/Client/api/app_api.py
ZSGF/Client/api/ding_talk_api.py
ZSGF/Client/api/external_account_api.py
ZSGF/Client/api/file_api.py
ZSGF/Client/api/o_auth_api.py
ZSGF/Client/api/order_api.py
ZSGF/Client/api/storage_api.py
ZSGF/Client/api/user_api.py
ZSGF/Client/api/user_currency_api.py
ZSGF/Client/api/user_friends_api.py
ZSGF/Client/api/user_location_api.py
ZSGF/Client/api/wechat_api.py
ZSGF/Client/models/__init__.py
ZSGF/Client/models/access_token_list_result.py
ZSGF/Client/models/access_token_list_result_api_response.py
ZSGF/Client/models/access_token_post_request.py
ZSGF/Client/models/access_token_put_request.py
ZSGF/Client/models/alipay_create_order_page_pay_request.py
ZSGF/Client/models/alipay_create_order_request.py
ZSGF/Client/models/alipay_create_order_wap_pay_request.py
ZSGF/Client/models/alipay_trade_query_response.py
ZSGF/Client/models/alipay_trade_query_response_api_response.py
ZSGF/Client/models/alipay_trade_refund_response.py
ZSGF/Client/models/alipay_trade_refund_response_api_response.py
ZSGF/Client/models/app_info_item.py
ZSGF/Client/models/app_info_result.py
ZSGF/Client/models/app_info_result_api_response.py
ZSGF/Client/models/app_property.py
ZSGF/Client/models/app_user_consent_model.py
ZSGF/Client/models/app_user_consent_model_list_api_response.py
ZSGF/Client/models/app_user_reset_email_request.py
ZSGF/Client/models/app_user_reset_phone_request.py
ZSGF/Client/models/app_user_reset_pwd_request.py
ZSGF/Client/models/authorize_result.py
ZSGF/Client/models/authorize_result_api_response.py
ZSGF/Client/models/bk_agent_resp_info.py
ZSGF/Client/models/boolean_api_response.py
ZSGF/Client/models/charge_info.py
