Metadata-Version: 2.4
Name: ZSGF.Client
Version: 2.1.2
Summary: 全部  API 文档
Home-page: https://github.com/wz101010/zsgf-python
Author: zashigaofa.com
Author-email: noreply@zashigaofa.com
Keywords: zashigaofa,全部  API 文档
Requires-Dist: urllib3<3.0.0,>=1.25.3
Requires-Dist: python-dateutil>=2.8.2
Requires-Dist: pydantic>=2
Requires-Dist: typing-extensions>=4.7.1
Dynamic: author
Dynamic: author-email
Dynamic: description-content-type
Dynamic: home-page
Dynamic: keywords
Dynamic: requires-dist
Dynamic: summary
